fast_edit_distance.cpython-313-x86_64-linux-gnu.so
fast_edit_distance-1.2.2.dist-info/LICENSE
fast_edit_distance-1.2.2.dist-info/METADATA
fast_edit_distance-1.2.2.dist-info/RECORD
fast_edit_distance-1.2.2.dist-info/WHEEL
fast_edit_distance-1.2.2.dist-info/top_level.txt
