Metadata-Version: 2.1
Name: fast_edit_distance
Version: 1.2.2
Summary: Implementation of edit distance calculation.
Author-email: Yupei You <youyupei@gmail.com>
License: MIT
Project-URL: Source, https://github.com/youyupei/fast_edit_distance
Classifier: Programming Language :: Python :: 3
Classifier: License :: OSI Approved :: MIT License
Classifier: Operating System :: OS Independent
Requires-Python: >=3.7
License-File: LICENSE
Requires-Dist: cython
